documents/__init__.py
optimed/__init__.py
optimed/wrappers/__init__.py
optimed/wrappers/calculations.py
optimed/wrappers/nifti.py
optimed/wrappers/operations.py
tests/test_calculations_utils.py
tests/test_nifti_utils.py
tests/test_operation_utils.py
optimed-0.2.4.dist-info/LICENSE
optimed-0.2.4.dist-info/METADATA
optimed-0.2.4.dist-info/WHEEL
optimed-0.2.4.dist-info/top_level.txt
optimed-0.2.4.dist-info/RECORD
