Metadata-Version: 2.2
Name: optimed
Version: 0.2.4
Summary: Optimed
Author-email: Roman Fitzjalen <info@bluemind.co>
License: Private Commercial License
Project-URL: Homepage, https://github.com/bluemindai/optimed.git
Project-URL: Issues, https://github.com/bluemindai/optimed/issues
Classifier: Programming Language :: Python :: 3
Classifier: Operating System :: OS Independent
Classifier: License :: OSI Approved :: Apache Software License
Requires-Python: >=3.9
License-File: LICENSE
Requires-Dist: cupy-cuda12x==13.0.0; platform_system != "Darwin"
Requires-Dist: pylibraft-cu12==24.8.1; platform_system != "Darwin"
Requires-Dist: numpy==1.26.3
Requires-Dist: nibabel==5.2.1
Requires-Dist: SimpleITK==2.3.1
Requires-Dist: pyyaml==6.0.2
Requires-Dist: xmltodict==0.14.2
Requires-Dist: scipy==1.13.1
